reverse_osmosis/__init__.py
reverse_osmosis/license.S.HTML
reverse_osmosis/mixer.S.HTML
reverse_osmosis/__later/later.S.HTML
reverse_osmosis/_clique/__init__.py
reverse_osmosis/_clique/group/__init__.py
reverse_osmosis/_licenses/license.S.HTML
reverse_osmosis/_licenses/notes/gpl-3.0-standalone.html
reverse_osmosis/_licenses/notes/license.S.HTML
reverse_osmosis/_status/status.proc.py
reverse_osmosis/_status/monitors/status_1.py
reverse_osmosis/business/business.S.HTML
reverse_osmosis/business/hygiene/hygiene.S.HTML
reverse_osmosis-1.0.0.dist-info/METADATA
reverse_osmosis-1.0.0.dist-info/WHEEL
reverse_osmosis-1.0.0.dist-info/top_level.txt
reverse_osmosis-1.0.0.dist-info/RECORD
