Metadata-Version: 2.1
Name: reverse_osmosis
Version: 1.0.0
License: 
Requires-Dist: volts
Requires-Dist: somatic
Requires-Dist: click
